mtbp3Lab/__init__.py
mtbp3Lab/data/test_lsr/testfolder1/testfile10
mtbp3Lab/data/test_lsr/testfolder1/testfile11
mtbp3Lab/data/test_lsr/testfolder1/testfile12
mtbp3Lab/data/test_lsr/testfolder2/testfile20
mtbp3Lab/data/test_lsr/testfolder2/testfile3
mtbp3Lab/statlab/__init__.py
mtbp3Lab/statlab/corr.py
mtbp3Lab/statlab/kappa.py
mtbp3Lab/util/__init__.py
mtbp3Lab/util/cdt.py
mtbp3Lab/util/cdtg.py
mtbp3Lab/util/lsr.py
mtbp3lab-0.1.1.dist-info/LICENSE
mtbp3lab-0.1.1.dist-info/METADATA
mtbp3lab-0.1.1.dist-info/WHEEL
mtbp3lab-0.1.1.dist-info/RECORD
